synapso_core/__init__.py
synapso_core/config_manager.py
synapso_core/cortex_manager.py
synapso_core/models.py
synapso_core/query_manager.py
synapso_core/synapso_logger.py
synapso_core/chunking/__init__.py
synapso_core/chunking/factory.py
synapso_core/chunking/interface.py
synapso_core/chunking/implementations/__init__.py
synapso_core/chunking/implementations/md/__init__.py
synapso_core/chunking/implementations/md/chonkie_recursive_chunker.py
synapso_core/chunking/implementations/md/langchain_markdown_chunker.py
synapso_core/cortex_watcher/__init__.py
synapso_core/cortex_watcher/cortex_watcher.py
synapso_core/data_store/__init__.py
synapso_core/data_store/data_models.py
synapso_core/data_store/factory.py
synapso_core/data_store/interfaces.py
synapso_core/data_store/backend/__init__.py
synapso_core/data_store/backend/sqlite/__init__.py
synapso_core/data_store/backend/sqlite/sqlite_backend_identifier.py
synapso_core/data_store/backend/sqlite/sqlite_meta_store.py
synapso_core/data_store/backend/sqlite/sqlite_private_store.py
synapso_core/data_store/backend/sqlite/sqlite_vector_store.py
synapso_core/data_store/backend/sqlite/utils.py
synapso_core/ingestor/__init__.py
synapso_core/ingestor/document_ingestor.py
synapso_core/reranker/__init__.py
synapso_core/reranker/bm25_reranker.py
synapso_core/reranker/factory.py
synapso_core/reranker/interface.py
synapso_core/summarizer/__init__.py
synapso_core/summarizer/factory.py
synapso_core/summarizer/instruct_summarizer.py
synapso_core/summarizer/interface.py
synapso_core/vectorizer/__init__.py
synapso_core/vectorizer/factory.py
synapso_core/vectorizer/interface.py
synapso_core/vectorizer/implementations/__init__.py
synapso_core/vectorizer/implementations/sentence_transformer_embeddings.py
synapso_core-0.2.0.dist-info/licenses/LICENSE
synapso_core-0.2.0.dist-info/METADATA
synapso_core-0.2.0.dist-info/WHEEL
synapso_core-0.2.0.dist-info/top_level.txt
synapso_core-0.2.0.dist-info/RECORD
